aliceio/__init__.py
aliceio/__meta__.py
aliceio/exceptions.py
aliceio/loggers.py
aliceio/py.typed
aliceio/client/__init__.py
aliceio/client/alice.py
aliceio/client/context_controller.py
aliceio/client/skill.py
aliceio/client/session/__init__.py
aliceio/client/session/aiohttp.py
aliceio/client/session/base.py
aliceio/client/session/middlewares/__init__.py
aliceio/client/session/middlewares/base.py
aliceio/client/session/middlewares/manager.py
aliceio/client/session/middlewares/request_logging.py
aliceio/dispatcher/__init__.py
aliceio/dispatcher/dispatcher.py
aliceio/dispatcher/flags.py
aliceio/dispatcher/router.py
aliceio/dispatcher/event/__init__.py
aliceio/dispatcher/event/alice.py
aliceio/dispatcher/event/bases.py
aliceio/dispatcher/event/event.py
aliceio/dispatcher/event/handler.py
aliceio/dispatcher/middlewares/__init__.py
aliceio/dispatcher/middlewares/base.py
aliceio/dispatcher/middlewares/error.py
aliceio/dispatcher/middlewares/manager.py
aliceio/dispatcher/middlewares/response_convert.py
aliceio/dispatcher/middlewares/user_context.py
aliceio/enums/__init__.py
aliceio/enums/audio_error.py
aliceio/enums/base.py
aliceio/enums/card.py
aliceio/enums/entity.py
aliceio/enums/file_type.py
aliceio/enums/http_method.py
aliceio/enums/update.py
aliceio/filters/__init__.py
aliceio/filters/base.py
aliceio/filters/exception.py
aliceio/filters/logic.py
aliceio/filters/magic_data.py
aliceio/filters/state.py
aliceio/fsm/__init__.py
aliceio/fsm/context.py
aliceio/fsm/state.py
aliceio/fsm/strategy.py
aliceio/fsm/middlewares/__init__.py
aliceio/fsm/middlewares/api_storage.py
aliceio/fsm/middlewares/fsm_context.py
aliceio/fsm/storage/__init__.py
aliceio/fsm/storage/api.py
aliceio/fsm/storage/base.py
aliceio/fsm/storage/memory.py
aliceio/fsm/storage/redis.py
aliceio/handlers/__init__.py
aliceio/handlers/account_linking_complete.py
aliceio/handlers/audio_player.py
aliceio/handlers/base.py
aliceio/handlers/button_pressed.py
aliceio/handlers/error.py
aliceio/handlers/message.py
aliceio-0.2.3.dist-info/METADATA
aliceio-0.2.3.dist-info/WHEEL
aliceio-0.2.3.dist-info/licenses/LICENSE
aliceio-0.2.3.dist-info/licenses/NOTICE
aliceio-0.2.3.dist-info/RECORD
